certbot_dns_websupport_v2/__init__.py
certbot_dns_websupport_v2/dns_websupport_v2.py
certbot_dns_websupport_v2-1.0.1.dist-info/LICENSE
certbot_dns_websupport_v2-1.0.1.dist-info/METADATA
certbot_dns_websupport_v2-1.0.1.dist-info/WHEEL
certbot_dns_websupport_v2-1.0.1.dist-info/entry_points.txt
certbot_dns_websupport_v2-1.0.1.dist-info/top_level.txt
certbot_dns_websupport_v2-1.0.1.dist-info/RECORD
