Metadata-Version: 2.1
Name: certbot-dns-websupport-v2
Version: 1.0.1
Summary: Websupport DNS Authenticator plugin for Certbot
Home-page: https://github.com/tfilo/certbot-dns-websupport-v2
Author: Tomáš Filo
Author-email: tfilosk@gmail.com
License: Apache
Classifier: Development Status :: 5 - Production/Stable
Classifier: Environment :: Plugins
Classifier: Intended Audience :: System Administrators
Classifier: License :: OSI Approved :: Apache Software License
Classifier: Operating System :: POSIX :: Linux
Classifier: Programming Language :: Python
Classifier: Programming Language :: Python :: 3
Classifier: Programming Language :: Python :: 3.8
Classifier: Programming Language :: Python :: 3.9
Classifier: Programming Language :: Python :: 3.10
Classifier: Programming Language :: Python :: 3.11
Classifier: Programming Language :: Python :: 3.12
Classifier: Topic :: Internet :: WWW/HTTP
Classifier: Topic :: Security
Classifier: Topic :: System :: Installation/Setup
Classifier: Topic :: System :: Networking
Classifier: Topic :: System :: Systems Administration
Classifier: Topic :: Utilities
Requires-Python: >=3.8
License-File: LICENSE
Requires-Dist: certbot >=2.11.0
Requires-Dist: setuptools
Requires-Dist: requests
Provides-Extra: docs
Requires-Dist: Sphinx >=1.0 ; extra == 'docs'
Requires-Dist: sphinx-rtd-theme ; extra == 'docs'
